jaims/__init__.py
jaims/agent.py
jaims/default_history_manager.py
jaims/default_tool_manager.py
jaims/entities.py
jaims/factories.py
jaims/function_tool_decorator.py
jaims/interfaces.py
jaims/adapters/__init__.py
jaims/adapters/anthropic_adapter/__init__.py
jaims/adapters/anthropic_adapter/adapter.py
jaims/adapters/google_generative_ai_adapter/__init__.py
jaims/adapters/google_generative_ai_adapter/adapter.py
jaims/adapters/mistral_adapter/__init__.py
jaims/adapters/mistral_adapter/adapter.py
jaims/adapters/openai_adapter/__init__.py
jaims/adapters/openai_adapter/adapter.py
jaims/adapters/shared/__init__.py
jaims/adapters/shared/exponential_backoff_operation.py
jaims/adapters/shared/image_utilities.py
jaims/adapters/vertexai_adapter/__init__.py
jaims/adapters/vertexai_adapter/adapter.py
jaims_py-2.0.0.dist-info/LICENSE
jaims_py-2.0.0.dist-info/METADATA
jaims_py-2.0.0.dist-info/WHEEL
jaims_py-2.0.0.dist-info/top_level.txt
jaims_py-2.0.0.dist-info/RECORD
