Metadata-Version: 2.1
Name: jaims-py
Version: 2.0.0
Summary: A Python package for creating LLM powered, agentic, platform agnostic software.
Home-page: https://github.com/dev-mush/jaims-py
Author: Marco Musella
License: MIT
Keywords: An extensible library to create LLM Agents and LLM based applications.
License-File: LICENSE
Requires-Dist: Pillow>=10.3.0
Requires-Dist: pydantic>=2.0.0
Requires-Dist: jsonref>=1.1.0
Provides-Extra: all
Requires-Dist: openai>=1.34.0; extra == "all"
Requires-Dist: tiktoken>=0.7.0; extra == "all"
Requires-Dist: google-generativeai>=0.6.0; extra == "all"
Requires-Dist: google-cloud-aiplatform>=1.0.0; extra == "all"
Requires-Dist: mistralai==0.4.2; extra == "all"
Requires-Dist: anthropic>=0.31.1; extra == "all"
Requires-Dist: anthropic[vertex]>=0.31.1; extra == "all"
Provides-Extra: anthropic
Requires-Dist: anthropic>=0.31.1; extra == "anthropic"
Provides-Extra: anthropic-all
Requires-Dist: anthropic>=0.31.1; extra == "anthropic-all"
Requires-Dist: anthropic[vertex]>=0.31.1; extra == "anthropic-all"
Provides-Extra: anthropic-vertex
Requires-Dist: anthropic[vertex]>=0.31.1; extra == "anthropic-vertex"
Provides-Extra: google
Requires-Dist: google-generativeai>=0.6.0; extra == "google"
Provides-Extra: mistral
Requires-Dist: mistralai==0.4.2; extra == "mistral"
Provides-Extra: openai
Requires-Dist: openai>=1.34.0; extra == "openai"
Requires-Dist: tiktoken>=0.7.0; extra == "openai"
Provides-Extra: vertexai
Requires-Dist: google-cloud-aiplatform>=1.0.0; extra == "vertexai"
